inferelator_velocity/__init__.py
inferelator_velocity/decay.py
inferelator_velocity/denoise_data.py
inferelator_velocity/program_genes.py
inferelator_velocity/program_graph.py
inferelator_velocity/programs.py
inferelator_velocity/times.py
inferelator_velocity/velocity.py
inferelator_velocity/metrics/__init__.py
inferelator_velocity/metrics/circcorrcoef.py
inferelator_velocity/metrics/information.py
inferelator_velocity/plotting/__init__.py
inferelator_velocity/plotting/mcv_summary.py
inferelator_velocity/plotting/program_times.py
inferelator_velocity/plotting/programs.py
inferelator_velocity/tests/__init__.py
inferelator_velocity/tests/_stubs.py
inferelator_velocity/tests/test_decay.py
inferelator_velocity/tests/test_denoise.py
inferelator_velocity/tests/test_graph.py
inferelator_velocity/tests/test_math.py
inferelator_velocity/tests/test_metrics.py
inferelator_velocity/tests/test_noise2self.py
inferelator_velocity/tests/test_programs.py
inferelator_velocity/tests/test_times.py
inferelator_velocity/tests/test_velocity.py
inferelator_velocity/utils/__init__.py
inferelator_velocity/utils/aggregation.py
inferelator_velocity/utils/graph.py
inferelator_velocity/utils/keys.py
inferelator_velocity/utils/math.py
inferelator_velocity/utils/mcv.py
inferelator_velocity/utils/misc.py
inferelator_velocity/utils/noise2self.py
inferelator_velocity-1.2.0.dist-info/LICENSE
inferelator_velocity-1.2.0.dist-info/METADATA
inferelator_velocity-1.2.0.dist-info/WHEEL
inferelator_velocity-1.2.0.dist-info/top_level.txt
inferelator_velocity-1.2.0.dist-info/RECORD
