Metadata-Version: 2.1
Name: inferelator_velocity
Version: 1.2.0
Summary: Inferelator-Velocity Calcualtes Dynamic Latent Parameters
Home-page: https://github.com/flatironinstitute/inferelator-velocity
Author: Chris Jackson
Author-email: cj59@nyu.edu
Maintainer: Chris Jackson
Maintainer-email: cj59@nyu.edu
License-File: LICENSE
Requires-Dist: numpy
Requires-Dist: pandas >=1.0
Requires-Dist: anndata >=0.8
Requires-Dist: scanpy
Requires-Dist: scipy
Requires-Dist: joblib
Requires-Dist: scikit-learn
Requires-Dist: tqdm
Requires-Dist: leidenalg
Requires-Dist: scself
